compose_to_rancher/__init__.py
compose_to_rancher-0.1.0a4.dist-info/DESCRIPTION.rst
compose_to_rancher-0.1.0a4.dist-info/METADATA
compose_to_rancher-0.1.0a4.dist-info/RECORD
compose_to_rancher-0.1.0a4.dist-info/WHEEL
compose_to_rancher-0.1.0a4.dist-info/entry_points.txt
compose_to_rancher-0.1.0a4.dist-info/metadata.json
compose_to_rancher-0.1.0a4.dist-info/top_level.txt
