Metadata-Version: 2.0
Name: compose-to-rancher
Version: 0.1.0a4
Summary: Convert Docker Compose V2 to Rancher compatible Docker Compose V1
Home-page: https://github.com/tiangolo/compose-to-rancher
Author: Sebastian Ramirez
Author-email: tiangolo@gmail.com
License: MIT
Keywords: setuptools development docker rancher compose
Platform: UNKNOWN
Classifier: Development Status :: 3 - Alpha
Classifier: Intended Audience :: Developers
Classifier: Topic :: Software Development :: Code Generators
Classifier: License :: OSI Approved :: MIT License
Classifier: Programming Language :: Python :: 2
Classifier: Programming Language :: Python :: 2.6
Classifier: Programming Language :: Python :: 2.7
Classifier: Programming Language :: Python :: 3
Classifier: Programming Language :: Python :: 3.3
Classifier: Programming Language :: Python :: 3.4
Classifier: Programming Language :: Python :: 3.5
Requires-Dist: pyyaml
